clesydecloud/__init__.py
clesydecloud/__main__.py
clesydecloud/client.py
clesydecloud/const.py
clesydecloud/data.py
clesydecloud/iot.py
clesydecloud/iot_certs.py
clesydecloud/iot_message.py
clesydecloud/iot_shadow.py
clesydecloud/provisioning.py
clesydecloud/py.typed
clesydecloud/remote.py
clesydecloud/status.py
clesydecloud/utils.py
clesyde_cloud_lib-0.1.16.dist-info/LICENSE
clesyde_cloud_lib-0.1.16.dist-info/METADATA
clesyde_cloud_lib-0.1.16.dist-info/WHEEL
clesyde_cloud_lib-0.1.16.dist-info/entry_points.txt
clesyde_cloud_lib-0.1.16.dist-info/RECORD
