Metadata-Version: 2.3
Name: clesyde_cloud_lib
Version: 0.1.16
Summary: Clesyde_Cloud_Lib
License: GPL-3.0
Author: Fabrice Dewasmes, Alain Rouen
Author-email: fabrice.dewasmes@gmail.com
Requires-Python: >=3.12.0,<4.0.0
Classifier: Development Status :: 2 - Pre-Alpha
Classifier: License :: OSI Approved :: GNU General Public License v3 (GPLv3)
Classifier: Programming Language :: Python :: 3
Classifier: Programming Language :: Python :: 3.12
Classifier: Programming Language :: Python :: 3.13
Requires-Dist: aiohttp (==3.12.15)
Requires-Dist: aiomqtt (>=2.3.2)
Requires-Dist: click (>=8.0.1)
Requires-Dist: dataclasses-json (>=0.6.7,<0.7.0)
Requires-Dist: snitun (==0.44.0)
Project-URL: Changelog, https://github.com/Clesyde-OS/cloud-lib/releases
Project-URL: Documentation, https://clesyde_cloud_lib.readthedocs.io
Project-URL: Homepage, https://github.com/fdewasmes/clesyde_cloud_lib
Project-URL: Repository, https://github.com/fdewasmes/clesyde_cloud_lib
